causationentropy/__init__.py
causationentropy/core/__init__.py
causationentropy/core/discovery.py
causationentropy/core/linalg.py
causationentropy/core/plotting.py
causationentropy/core/stats.py
causationentropy/core/information/__init__.py
causationentropy/core/information/conditional_mutual_information.py
causationentropy/core/information/entropy.py
causationentropy/core/information/mutual_information.py
causationentropy/datasets/__init__.py
causationentropy/datasets/synthetic.py
causationentropy/graph/__init__.py
causationentropy/graph/utils.py
causationentropy/tests/__init__.py
causationentropy/tests/test_data_integration.py
causationentropy/tests/test_discovery.py
causationentropy/tests/test_graph_utils.py
causationentropy/tests/test_integration.py
causationentropy/tests/test_linalg.py
causationentropy/tests/test_plotting.py
causationentropy/tests/test_stats.py
causationentropy/tests/test_synthetic.py
causationentropy/tests/core/information/__init__.py
causationentropy/tests/core/information/test_conditional_mutual_information.py
causationentropy/tests/core/information/test_entropy.py
causationentropy/tests/core/information/test_mutual_information.py
causationentropy-1.1.0.dist-info/licenses/LICENSE
causationentropy-1.1.0.dist-info/METADATA
causationentropy-1.1.0.dist-info/WHEEL
causationentropy-1.1.0.dist-info/top_level.txt
causationentropy-1.1.0.dist-info/RECORD
