Metadata-Version: 2.4
Name: causationentropy
Version: 1.1.0
Summary: Causal network discovery using optimal causation entropy
Author-email: Kevin Slote <kslote1@gmail.com>
Project-URL: Homepage, https://github.com/Center-For-Complex-Systems-Science/causationentropy
Project-URL: Repository, https://github.com/Center-For-Complex-Systems-Science/causationentropy
Project-URL: Documentation, https://causationentropy.readthedocs.io/en/latest/
Project-URL: Bug Tracker, https://github.com/Center-For-Complex-Systems-Science/causationentropy/issues
Keywords: causality,causal-inference,causal-discovery,causal-network,granger-causality,causation-entropy,entropy,mutual-information,information-theory,time-series,multivariate-time-series,graph-theory,network-science,bayesian-networks,markov-models,statistical-inference,machine-learning,dimensionality-reduction,complex-systems,dynamical-systems,neuroscience,computational-biology,epidemiology,econometrics
Classifier: Development Status :: 3 - Alpha
Classifier: Intended Audience :: Science/Research
Classifier: License :: OSI Approved :: MIT License
Classifier: Operating System :: OS Independent
Classifier: Programming Language :: Python :: 3
Classifier: Programming Language :: Python :: 3.8
Classifier: Programming Language :: Python :: 3.9
Classifier: Programming Language :: Python :: 3.10
Classifier: Programming Language :: Python :: 3.11
Classifier: Topic :: Scientific/Engineering
Classifier: Topic :: Scientific/Engineering :: Information Analysis
Classifier: Topic :: Scientific/Engineering :: Mathematics
Classifier: Topic :: Scientific/Engineering :: Physics
Classifier: Topic :: Scientific/Engineering :: Artificial Intelligence
Requires-Python: >=3.8
License-File: LICENSE
Requires-Dist: numpy>=1.20.0
Requires-Dist: pandas>=1.3.0
Requires-Dist: scipy>=1.7.0
Requires-Dist: scikit-learn>=1.0.0
Requires-Dist: networkx>=2.6.0
Requires-Dist: matplotlib>=3.4.0
Requires-Dist: tqdm>=4.60.0
Requires-Dist: tigramite>=5.0.0
Provides-Extra: dev
Requires-Dist: pytest>=6.0; extra == "dev"
Requires-Dist: pytest-cov>=2.0; extra == "dev"
Requires-Dist: black>=22.0; extra == "dev"
Requires-Dist: flake8>=4.0; extra == "dev"
Requires-Dist: isort>=5.0; extra == "dev"
Requires-Dist: mypy>=0.900; extra == "dev"
Requires-Dist: pre-commit>=2.15.0; extra == "dev"
Requires-Dist: tigramite>=5.0.0; extra == "dev"
Provides-Extra: docs
Requires-Dist: sphinx>=4.0; extra == "docs"
Requires-Dist: sphinx-rtd-theme>=1.0; extra == "docs"
Requires-Dist: numpydoc>=1.0; extra == "docs"
Requires-Dist: jupyter-book>=0.12.0; extra == "docs"
Provides-Extra: plotting
Requires-Dist: seaborn>=0.11; extra == "plotting"
Requires-Dist: plotly>=5.0; extra == "plotting"
Requires-Dist: graphviz>=0.17; extra == "plotting"
Provides-Extra: all
Requires-Dist: causationentropy[dev,docs,plotting]; extra == "all"
Dynamic: license-file
